[
	{
		"__TYPE__": "SharedSliceContent",
		"variation": "default",
		"primary": {
			"text": {
				"__TYPE__": "StructuredTextContent",
				"value": [
					{
						"type": "paragraph",
						"content": {
							"text": "Cillum elit incididunt nulla dolore eiusmod in sit ea reprehenderit minim labore."
						}
					}
				]
			},
			"title": {
				"__TYPE__": "FieldContent",
				"value": "receive",
				"type": "Text"
			},
			"image": {
				"origin": {
					"id": "main",
					"url": "https://images.unsplash.com/photo-1515378791036-0648a3ef77b2",
					"width": 5616,
					"height": 3744
				},
				"url": "https://images.unsplash.com/photo-1515378791036-0648a3ef77b2",
				"width": 5616,
				"height": 3744,
				"edit": {
					"zoom": 1,
					"crop": {
						"x": 0,
						"y": 0
					},
					"background": "transparent"
				},
				"credits": null,
				"alt": null,
				"__TYPE__": "ImageContent",
				"thumbnails": {}
			},
			"bg_symbol_direction": {
				"__TYPE__": "FieldContent",
				"value": "Arrows facing up",
				"type": "Select"
			},
			"bg_symbol_position": {
				"__TYPE__": "FieldContent",
				"value": "right",
				"type": "Select"
			}
		},
		"items": []
	},
	{
		"__TYPE__": "SharedSliceContent",
		"variation": "textRightImageLeft",
		"primary": {
			"title": {
				"__TYPE__": "FieldContent",
				"value": "loss",
				"type": "Text"
			},
			"text": {
				"__TYPE__": "StructuredTextContent",
				"value": [
					{
						"type": "paragraph",
						"content": {
							"text": "Incididunt commodo eiusmod cillum minim dolore eiusmod dolore culpa est amet occaecat aute."
						}
					}
				]
			},
			"image": {
				"origin": {
					"id": "main",
					"url": "https://images.unsplash.com/photo-1579931794097-0ad001e51edb",
					"width": 3958,
					"height": 3958
				},
				"url": "https://images.unsplash.com/photo-1579931794097-0ad001e51edb",
				"width": 3958,
				"height": 3958,
				"edit": {
					"zoom": 1,
					"crop": {
						"x": 0,
						"y": 0
					},
					"background": "transparent"
				},
				"credits": null,
				"alt": null,
				"__TYPE__": "ImageContent",
				"thumbnails": {}
			},
			"bg_symbol_direction": {
				"__TYPE__": "FieldContent",
				"value": "Arrows facing up",
				"type": "Select"
			},
			"bg_symbol_position": {
				"__TYPE__": "FieldContent",
				"value": "center",
				"type": "Select"
			}
		},
		"items": [
			{
				"__TYPE__": "GroupItemContent",
				"value": []
			}
		]
	},
	{
		"__TYPE__": "SharedSliceContent",
		"variation": "textTopImageBottom",
		"primary": {
			"title": {
				"__TYPE__": "FieldContent",
				"value": "fourth",
				"type": "Text"
			},
			"text": {
				"__TYPE__": "StructuredTextContent",
				"value": [
					{
						"type": "paragraph",
						"content": {
							"text": "Voluptate est eu exercitation id consectetur fugiat."
						}
					}
				]
			},
			"image": {
				"origin": {
					"id": "main",
					"url": "https://images.unsplash.com/photo-1600804931749-2da4ce26c869",
					"width": 3199,
					"height": 3199
				},
				"url": "https://images.unsplash.com/photo-1600804931749-2da4ce26c869",
				"width": 3199,
				"height": 3199,
				"edit": {
					"zoom": 1,
					"crop": {
						"x": 0,
						"y": 0
					},
					"background": "transparent"
				},
				"credits": null,
				"alt": null,
				"__TYPE__": "ImageContent",
				"thumbnails": {}
			},
			"bg_symbol_direction": {
				"__TYPE__": "FieldContent",
				"value": "Arrows facing up",
				"type": "Select"
			},
			"bg_symbol_position": {
				"__TYPE__": "FieldContent",
				"value": "center",
				"type": "Select"
			}
		},
		"items": [
			{
				"__TYPE__": "GroupItemContent",
				"value": []
			}
		]
	}
]